sd_connector/__init__.py
sd_connector/sd_connector.py
os2mo_sd_connector-0.0.2.dist-info/LICENSE
os2mo_sd_connector-0.0.2.dist-info/METADATA
os2mo_sd_connector-0.0.2.dist-info/WHEEL
os2mo_sd_connector-0.0.2.dist-info/top_level.txt
os2mo_sd_connector-0.0.2.dist-info/RECORD
